rexam_item_editor/__init__.py
rexam_item_editor/__main__.py
rexam_item_editor/cli.py
rexam_item_editor/consts.py
rexam_item_editor/misc.py
rexam_item_editor/sysinfo.py
rexam_item_editor/gui/__init__.py
rexam_item_editor/gui/dialogs.py
rexam_item_editor/gui/essb.png
rexam_item_editor/gui/exam_compiler.py
rexam_item_editor/gui/gui_misc.py
rexam_item_editor/gui/json_settings.py
rexam_item_editor/gui/log.py
rexam_item_editor/gui/mainwin.py
rexam_item_editor/rexam/__init__.py
rexam_item_editor/rexam/exam.py
rexam_item_editor/rexam/extypes.py
rexam_item_editor/rexam/filepath.py
rexam_item_editor/rexam/git_info.py
rexam_item_editor/rexam/issue.py
rexam_item_editor/rexam/item.py
rexam_item_editor/rexam/item_database.py
rexam_item_editor/rexam/r_render.py
rexam_item_editor/rexam/rmd_file.py
rexam_item_editor/rexam/rmd_file_list.py
rexam_item_editor/templates/TemplateBlankCombination.Rmd
rexam_item_editor/templates/TemplateBlankNumber.Rmd
rexam_item_editor/templates/TemplateBlankTextEssay.Rmd
rexam_item_editor/templates/TemplateMultipleAnswer.Rmd
rexam_item_editor/templates/TemplateMultipleChoice.Rmd
rexam_item_editor/templates/__init__.py
rexam_item_editor-0.2.11.post2.dist-info/LICENSE
rexam_item_editor-0.2.11.post2.dist-info/METADATA
rexam_item_editor-0.2.11.post2.dist-info/WHEEL
rexam_item_editor-0.2.11.post2.dist-info/entry_points.txt
rexam_item_editor-0.2.11.post2.dist-info/top_level.txt
rexam_item_editor-0.2.11.post2.dist-info/RECORD
