Metadata-Version: 2.1
Name: rexam-item-editor
Version: 0.2.11.post2
Summary: Maintaining and editing databases of RExam items
Home-page: https://github.com/lindemann09/rexam-item-editor
Author: Oliver Lindemann
Author-email: lindemann@cognitive-psychology.eu
License: MIT licence
Platform: UNKNOWN
Classifier: Intended Audience :: Education
Classifier: Intended Audience :: Science/Research
Classifier: License :: OSI Approved :: MIT License
Classifier: Operating System :: OS Independent
Classifier: Programming Language :: Python
Classifier: Programming Language :: Python :: 3
Classifier: Topic :: Scientific/Engineering
Requires-Dist: PyYAML (>=5.4)
Requires-Dist: appdirs (>=1.4)
Requires-Dist: pysimplegui (>=4.33)
Provides-Extra: rendering
Requires-Dist: Markdown (>=3.3) ; extra == 'rendering'
Requires-Dist: rpy2 (>=3.4.3) ; extra == 'rendering'
